baam/__init__.py
baam/cli.py
baam-0.0.3.dist-info/METADATA
baam-0.0.3.dist-info/WHEEL
baam-0.0.3.dist-info/entry_points.txt
baam-0.0.3.dist-info/top_level.txt
baam-0.0.3.dist-info/RECORD
