Metadata-Version: 2.1
Name: baam
Version: 0.0.3
Summary: Deploys docker apps
Home-page: https://github.com/jpedro/baam
Download-URL: https://github.com/jpedro/baam/tarball/master
Author: jpedro
Author-email: jpedro.barbosa@gmail.com
License: MIT
Keywords: deploy docker apps
Classifier: Development Status :: 3 - Alpha
Classifier: Intended Audience :: Developers
Classifier: Topic :: Software Development :: Build Tools
Classifier: License :: OSI Approved :: MIT License
Classifier: Programming Language :: Python :: 3
Requires-Python: >=3
Requires-Dist: pyyaml
